README.md
setup.py
hottings/__init__.py
hottings/monitors.py
hottings/version.py
hottings.egg-info/PKG-INFO
hottings.egg-info/SOURCES.txt
hottings.egg-info/dependency_links.txt
hottings.egg-info/entry_points.txt
hottings.egg-info/requires.txt
hottings.egg-info/top_level.txt
sample/__init__.py
sample/demo.py