Metadata-Version: 1.0
Name: hottings
Version: 0.0.7
Summary: A command line tool to manage hot reload tasks
Home-page: https://github.com/jeremaihloo/hottings
Author: jeremaihloo
Author-email: jeremaihloo1024@gmail.com
License: UNKNOWN
Project-URL: Bug Reports, https://github.com/jeremaihloo/hottings/issues
Project-URL: Source, https://github.com/jeremaihloo/hottings
Platform: UNKNOWN
